pvshepherd/LICENSE
pvshepherd/__init__.py
pvshepherd/_audio.py
pvshepherd/_firmware.py
pvshepherd/_gui_param.py
pvshepherd/_hardware.py
pvshepherd/_language_info.py
pvshepherd/_param.py
pvshepherd/shepherd.py
pvshepherd/asset/clipboard_white.png
pvshepherd/asset/loading.gif
pvshepherd/asset/mic_white.png
pvshepherd/asset/picovoice.png
pvshepherd/asset/pv_wordmark.jpg
pvshepherd/asset/save_white.png
pvshepherd/firmware/.gitattributes
pvshepherd/firmware/imxrt1050-evkb-demo-ar.axf
pvshepherd/firmware/imxrt1050-evkb-demo-de.axf
pvshepherd/firmware/imxrt1050-evkb-demo-en.axf
pvshepherd/firmware/imxrt1050-evkb-demo-es.axf
pvshepherd/firmware/imxrt1050-evkb-demo-fa.axf
pvshepherd/firmware/imxrt1050-evkb-demo-fr.axf
pvshepherd/firmware/imxrt1050-evkb-demo-hi.axf
pvshepherd/firmware/imxrt1050-evkb-demo-it.axf
pvshepherd/firmware/imxrt1050-evkb-demo-ja.axf
pvshepherd/firmware/imxrt1050-evkb-demo-ko.axf
pvshepherd/firmware/imxrt1050-evkb-demo-nl.axf
pvshepherd/firmware/imxrt1050-evkb-demo-pl.axf
pvshepherd/firmware/imxrt1050-evkb-demo-pt.axf
pvshepherd/firmware/imxrt1050-evkb-demo-ru.axf
pvshepherd/firmware/imxrt1050-evkb-demo-sv.axf
pvshepherd/firmware/imxrt1050-evkb-demo-vn.axf
pvshepherd/firmware/imxrt1050-evkb-demo-zh.axf
pvshepherd/firmware/stm32f407g-disc1-demo-ar.elf
pvshepherd/firmware/stm32f407g-disc1-demo-de.elf
pvshepherd/firmware/stm32f407g-disc1-demo-en.elf
pvshepherd/firmware/stm32f407g-disc1-demo-es.elf
pvshepherd/firmware/stm32f407g-disc1-demo-fa.elf
pvshepherd/firmware/stm32f407g-disc1-demo-fr.elf
pvshepherd/firmware/stm32f407g-disc1-demo-hi.elf
pvshepherd/firmware/stm32f407g-disc1-demo-it.elf
pvshepherd/firmware/stm32f407g-disc1-demo-ja.elf
pvshepherd/firmware/stm32f407g-disc1-demo-ko.elf
pvshepherd/firmware/stm32f407g-disc1-demo-nl.elf
pvshepherd/firmware/stm32f407g-disc1-demo-pl.elf
pvshepherd/firmware/stm32f407g-disc1-demo-pt.elf
pvshepherd/firmware/stm32f407g-disc1-demo-ru.elf
pvshepherd/firmware/stm32f407g-disc1-demo-sv.elf
pvshepherd-3.0.0.dist-info/METADATA
pvshepherd-3.0.0.dist-info/WHEEL
pvshepherd-3.0.0.dist-info/entry_points.txt
pvshepherd-3.0.0.dist-info/top_level.txt
pvshepherd-3.0.0.dist-info/RECORD
