Metadata-Version: 2.1
Name: pvshepherd
Version: 3.0.0
Summary: Shepherd
Home-page: https://github.com/Picovoice/picovoice
Author: Picovoice
Author-email: hello@picovoice.ai
Classifier: Development Status :: 3 - Alpha
Classifier: License :: Free for non-commercial use
Classifier: Operating System :: OS Independent
Classifier: Programming Language :: Python :: 3
Classifier: Topic :: Multimedia :: Sound/Audio :: Speech
Requires-Python: >=3.6
Requires-Dist: pyserial (>=3.5)
Requires-Dist: matplotlib (>=3.3.3)
Requires-Dist: bitstring (>=3.1.7)
Requires-Dist: Pillow (>=8.1.0)
